networking_odl/__init__.py
networking_odl/_i18n.py
networking_odl/bgpvpn/__init__.py
networking_odl/bgpvpn/odl_v2.py
networking_odl/ceilometer/__init__.py
networking_odl/ceilometer/network/__init__.py
networking_odl/ceilometer/network/statistics/__init__.py
networking_odl/ceilometer/network/statistics/opendaylight_v2/__init__.py
networking_odl/ceilometer/network/statistics/opendaylight_v2/client.py
networking_odl/ceilometer/network/statistics/opendaylight_v2/driver.py
networking_odl/cmd/__init__.py
networking_odl/cmd/analyze_journal.py
networking_odl/cmd/set_ovs_hostconfigs.py
networking_odl/cmd/test_setup_hostconfigs.sh
networking_odl/common/__init__.py
networking_odl/common/callback.py
networking_odl/common/client.py
networking_odl/common/config.py
networking_odl/common/constants.py
networking_odl/common/exceptions.py
networking_odl/common/filters.py
networking_odl/common/lightweight_testing.py
networking_odl/common/odl_features.py
networking_odl/common/postcommit.py
networking_odl/common/utils.py
networking_odl/common/websocket_client.py
networking_odl/db/__init__.py
networking_odl/db/db.py
networking_odl/db/head.py
networking_odl/db/models.py
networking_odl/db/migration/__init__.py
networking_odl/db/migration/alembic_migrations/README
networking_odl/db/migration/alembic_migrations/__init__.py
networking_odl/db/migration/alembic_migrations/env.py
networking_odl/db/migration/alembic_migrations/script.py.mako
networking_odl/db/migration/alembic_migrations/versions/CONTRACT_HEAD
networking_odl/db/migration/alembic_migrations/versions/EXPAND_HEAD
networking_odl/db/migration/alembic_migrations/versions/b89a299e19f9_initial_branchpoint.py
networking_odl/db/migration/alembic_migrations/versions/mitaka/contract/383acb0d38a0_initial_contract.py
networking_odl/db/migration/alembic_migrations/versions/mitaka/expand/247501328046_initial_expand.py
networking_odl/db/migration/alembic_migrations/versions/mitaka/expand/37e242787ae5_opendaylight_neutron_mechanism_driver_.py
networking_odl-22.0.0.dist-info/AUTHORS
networking_odl-22.0.0.dist-info/LICENSE
networking_odl-22.0.0.dist-info/METADATA
networking_odl-22.0.0.dist-info/WHEEL
networking_odl-22.0.0.dist-info/entry_points.txt
networking_odl-22.0.0.dist-info/pbr.json
networking_odl-22.0.0.dist-info/top_level.txt
networking_odl-22.0.0.dist-info/RECORD
